LICENSE
MANIFEST.in
README.rst
setup.cfg
setup.py
versioneer.py
artellapipe/__init__.py
artellapipe/libs/__init__.py
artellapipe/libs/ffmpeg/__init__.py
artellapipe/libs/ffmpeg/__logging__.ini
artellapipe/libs/ffmpeg/__version__.py
artellapipe/libs/ffmpeg/_version.py
artellapipe/libs/ffmpeg/core/__init__.py
artellapipe/libs/ffmpeg/core/ffmpeglib.py
artellapipe/libs/ffmpeg/externals/exe/windows/64bit/ffmpeg/LICENSE.txt
artellapipe/libs/ffmpeg/externals/exe/windows/64bit/ffmpeg/README.txt
artellapipe/libs/ffmpeg/externals/exe/windows/64bit/ffmpeg/VERSION.txt
artellapipe/libs/ffmpeg/externals/exe/windows/64bit/ffmpeg/bin/ffmpeg.exe
artellapipe/libs/ffmpeg/externals/exe/windows/64bit/ffmpeg/presets/ffprobe.xsd
artellapipe/libs/ffmpeg/externals/exe/windows/64bit/ffmpeg/presets/libvpx-1080p.ffpreset
artellapipe/libs/ffmpeg/externals/exe/windows/64bit/ffmpeg/presets/libvpx-1080p50_60.ffpreset
artellapipe/libs/ffmpeg/externals/exe/windows/64bit/ffmpeg/presets/libvpx-360p.ffpreset
artellapipe/libs/ffmpeg/externals/exe/windows/64bit/ffmpeg/presets/libvpx-720p.ffpreset
artellapipe/libs/ffmpeg/externals/exe/windows/64bit/ffmpeg/presets/libvpx-720p50_60.ffpreset
artellapipe_libs_ffmpeg.egg-info/PKG-INFO
artellapipe_libs_ffmpeg.egg-info/SOURCES.txt
artellapipe_libs_ffmpeg.egg-info/dependency_links.txt
artellapipe_libs_ffmpeg.egg-info/not-zip-safe
artellapipe_libs_ffmpeg.egg-info/requires.txt
artellapipe_libs_ffmpeg.egg-info/top_level.txt
tests/__init__.py
tests/test_general.py