Metadata-Version: 2.1
Name: artellapipe-libs-ffmpeg
Version: 0.0.4
Summary: FFMpeg libraries for ArtellaPipe
Home-page: https://github.com/ArtellaPipe/artellapipe-libs-ffmpeg
Author: Tomas Poveda
Author-email: tpovedatd@gmail.com
License: MIT
Platform: UNKNOWN
Provides-Extra: dev
Provides-Extra: test
